{
  "customName": "Folding Chair",
  "guid": "856bcd36-2d70-c321-dbe1-74bbada2a3cb",
  "parentGuid": null,
  "hierarchyOrder": 13.5,
  "isExposed": false,
  "components": [
    {
      "nameInCode": "Transform",
      "nameOfSlot": "Transform",
      "properties": [
        {
          "name": "position",
          "type": "Vector3",
          "fixedValue": {
            "x": 10.7096,
            "y": 0.200851411,
            "z": 6.22129536
          }
        },
        {
          "name": "rotation",
          "type": "Quaternion",
          "fixedValue": {
            "x": 0.0,
            "y": 0.0,
            "z": 0.0,
            "w": 1.0
          }
        },
        {
          "name": "scale",
          "type": "Vector3",
          "fixedValue": {
            "x": 1.0,
            "y": 1.0,
            "z": 1.0
          }
        }
      ]
    },
    {
      "nameInCode": "GLTFShape",
      "nameOfSlot": "Shape",
      "properties": [
        {
          "name": "asset",
          "type": "Asset",
          "fixedValue": "27cfd632-905a-4659-81cb-62a9e3c0d0ba"
        },
        {
          "name": "visible",
          "type": "Boolean",
          "fixedValue": true
        },
        {
          "name": "withCollisions",
          "type": "Boolean",
          "fixedValue": true
        },
        {
          "name": "isPointerBlocker",
          "type": "Boolean",
          "fixedValue": true
        }
      ]
    }
  ],
  "dclEditVersionNumber": "1.0.5"
}